healthcard/__init__.py
healthcard/address.py
healthcard/exceptions.py
healthcard/insurance.py
healthcard/patient.py
healthcard/reader.py
healthcard/utils.py
python_healthcard-1.0.5.dist-info/LICENSE
python_healthcard-1.0.5.dist-info/METADATA
python_healthcard-1.0.5.dist-info/WHEEL
python_healthcard-1.0.5.dist-info/top_level.txt
python_healthcard-1.0.5.dist-info/RECORD
