Metadata-Version: 2.1
Name: python-healthcard
Version: 1.0.5
Summary: A module to read german health insurance cards with python
Home-page: https://github.com/Blueshoe/python-healthcard/
Author: Blueshoe
Author-email: robert@blueshoe.de
License: MIT
Platform: UNKNOWN
License-File: LICENSE
Requires-Dist: pyscard (==1.9.6)
Requires-Dist: lxml (==4.6.5)
